python_codemagic_api/__init__.py
python_codemagic_api/base_endpoint.py
python_codemagic_api/codemagic_api.py
python_codemagic_api/exceptions.py
python_codemagic_api/endpoints/__init__.py
python_codemagic_api/endpoints/applications.py
python_codemagic_api/endpoints/artifacts.py
python_codemagic_api/endpoints/builds.py
python_codemagic_api/endpoints/caches.py
python_codemagic_api/endpoints/teams.py
python_codemagic_api/endpoints/__pycache__/__init__.cpython-312.pyc
python_codemagic_api/endpoints/__pycache__/applications.cpython-312.pyc
python_codemagic_api/endpoints/__pycache__/artifacts.cpython-312.pyc
python_codemagic_api/endpoints/__pycache__/builds.cpython-312.pyc
python_codemagic_api/endpoints/__pycache__/caches.cpython-312.pyc
python_codemagic_api/endpoints/__pycache__/teams.cpython-312.pyc
python_codemagic_api/utils/__init__.py
python_codemagic_api/utils/applications_utils.py
python_codemagic_api/utils/__pycache__/__init__.cpython-312.pyc
python_codemagic_api/utils/__pycache__/applications_utils.cpython-312.pyc
python_codemagic_api-0.0.12.dist-info/licenses/LICENSE
python_codemagic_api-0.0.12.dist-info/METADATA
python_codemagic_api-0.0.12.dist-info/WHEEL
python_codemagic_api-0.0.12.dist-info/top_level.txt
python_codemagic_api-0.0.12.dist-info/RECORD
