Metadata-Version: 2.4
Name: python_codemagic_api
Version: 0.0.12
Summary: Python API wrapper for Codemagic
Author-email: Benjamin Hubbell <bdhubbell@icloud.com>
License: MIT License
Classifier: Development Status :: 2 - Pre-Alpha
Classifier: Intended Audience :: Developers
Classifier: License :: OSI Approved :: MIT License
Classifier: Programming Language :: Python :: 3
Classifier: Topic :: Software Development :: Libraries
License-File: LICENSE
Requires-Dist: requests
Dynamic: license-file
